{
  "interactionModel": {
    "languageModel": {
      "invocationName": "地震避難チェックリスト",
      "intents": [
        {
          "name": "AMAZON.CancelIntent",
          "samples": []
        },
        {
          "name": "AMAZON.HelpIntent",
          "samples": []
        },
        {
          "name": "AMAZON.StopIntent",
          "samples": []
        },
        {
          "name": "AskRefugeCheckListIntent",
          "slots": [],
          "samples": [
            "避難前にやるべきことを教えて",
            "避難前にやるべきことはなに",
            "避難前にやるべきこと",
            "避難前にやること",
            "避難前に確認することを教えて",
            "避難前に確認することはなに",
            "避難前に確認すること",
            "避難前に確認するものを教えて",
            "避難前に確認するものはなに",
            "避難前に確認するもの",
            "避難前の確認",
            "避難前の確認しないといけないこと",
            "避難前の確認する内容",
            "避難前の確認リストを教えて",
            "避難前の確認リスト",
            "避難リスト",
            "リストを読み上げて"
          ]
        },
        {
          "name": "AskPrepareIntent",
          "slots": [],
          "samples": [
            "事前に準備しておくべきことはありますか",
            "事前に準備しておくべきことはなに",
            "事前に準備しておくべきことは",
            "事前に準備しておくべきことを教えて",
            "事前に準備しておくべきこと",
            "事前準備リストを教えて",
            "事前準備リスト"
          ]
        }
      ]
    }
  }
}
